philip/__init__.py
philip/__main__.py
philip/cli.py
philip/pip.py
philip/pipfile.py
philip/piptools.py
philip-0.0.0.dist-info/DESCRIPTION.rst
philip-0.0.0.dist-info/METADATA
philip-0.0.0.dist-info/RECORD
philip-0.0.0.dist-info/WHEEL
philip-0.0.0.dist-info/entry_points.txt
philip-0.0.0.dist-info/metadata.json
philip-0.0.0.dist-info/top_level.txt
